Metadata-Version: 2.1
Name: lizard
Version: 1.20.0
Summary: A code analyzer without caring the C/C++ header files. It works with Java, C/C++, JavaScript, Python, Ruby, Swift, Objective C. Metrics includes cyclomatic complexity number etc.
Home-page: http://www.lizard.ws
Author: Terry Yin
Author-email: terry@odd-e.com
License: MIT
Download-URL: https://pypi.python.org/lizard/
Project-URL: Source, https://github.com/terryyin/lizard
Platform: any
Classifier: Development Status :: 5 - Production/Stable
Classifier: Intended Audience :: Developers
Classifier: Intended Audience :: End Users/Desktop
Classifier: License :: Freeware
Classifier: Operating System :: POSIX
Classifier: Operating System :: Microsoft :: Windows
Classifier: Operating System :: MacOS :: MacOS X
Classifier: Topic :: Software Development :: Quality Assurance
Classifier: Programming Language :: C
Classifier: Programming Language :: C++
Classifier: Programming Language :: Java
Classifier: Programming Language :: JavaScript
Classifier: Programming Language :: Objective C
Classifier: Programming Language :: Python
Classifier: Programming Language :: Python :: 3.8
Classifier: Programming Language :: Python :: 3.9
Classifier: Programming Language :: Python :: 3.10
Classifier: Programming Language :: Python :: 3.11
License-File: LICENSE.txt
Requires-Dist: pygments
Requires-Dist: pathspec
